{
    "patchInfo": {
        "version":"1.1",
        "title":"Galactic Roaming",
        "releaseDate":"07.06.2023",
        "weeksCount":6,
        "events":[
            {
                "eventTitle":"Starhunt Game",
                "startDate":"07.06.2023",
                "endDate":"19.07.2023",
                "stellarJadesAmount":620
            },
            {
                "eventTitle":"Everwinter City Museum Ledger of Curiosities",
                "startDate":"09.07.2023",
                "endDate":"07.08.2023",
                "stellarJadesAmount":1000
            },
            {
                "eventTitle":"Lab Assistants in Position",
                "startDate":"19.06.2023",
                "endDate":"03.07.2023",
                "stellarJadesAmount":500
            },
            {
                "eventTitle":"Stellar Flare",
                "startDate":"28.06.2023",
                "endDate":"10.07.2023",
                "stellarJadesAmount":500
            }
        ],
        "banners":[]
    }
}