{
  "stats": {
    "users": 268126,
    "total_pulls": 14674610,
    "total_pulls_before_4": 14643716,
    "total_pulls_before_5": 13225620,
    "total_pulls_5": 225494,
    "total_pulls_4": 1919777,
    "avg_chance_4": 0.13109903,
    "avg_chance_5": 0.017049788,
    "count_win_5": 96345,
    "count_lose_5": 70365,
    "cur_pity_4": 4,
    "cur_pity_5": 42,
    "by_rollnum_pulls_all": {
      "1": 255709,
      "2": 255614,
      "3": 255052,
      "4": 254379,
      "5": 253696,
      "6": 252519,
      "7": 251423,
      "8": 250254,
      "9": 248897,
      "10": 247499,
      "11": 244741,
      "12": 242633,
      "13": 240549,
      "14": 238481,
      "15": 236267,
      "16": 233998,
      "17": 231758,
      "18": 229503,
      "19": 227369,
      "20": 225331,
      "21": 222430,
      "22": 220127,
      "23": 217850,
      "24": 215731,
      "25": 213601,
      "26": 211395,
      "27": 209204,
      "28": 207177,
      "29": 205196,
      "30": 203179,
      "31": 200606,
      "32": 198669,
      "33": 196556,
      "34": 194610,
      "35": 192729,
      "36": 190708,
      "37": 188872,
      "38": 186999,
      "39": 185082,
      "40": 183164,
      "41": 181067,
      "42": 179325,
      "43": 177601,
      "44": 175879,
      "45": 174078,
      "46": 172302,
      "47": 170694,
      "48": 168988,
      "49": 167319,
      "50": 165779,
      "51": 163854,
      "52": 162353,
      "53": 160656,
      "54": 159205,
      "55": 157687,
      "56": 156204,
      "57": 154768,
      "58": 153283,
      "59": 151874,
      "60": 150532,
      "61": 148941,
      "62": 147546,
      "63": 146194,
      "64": 144887,
      "65": 143555,
      "66": 142141,
      "67": 140831,
      "68": 139565,
      "69": 138216,
      "70": 136769,
      "71": 135270,
      "72": 133892,
      "73": 132516,
      "74": 131242,
      "75": 122104,
      "76": 106454,
      "77": 86579,
      "78": 65181,
      "79": 45248,
      "80": 28715,
      "81": 16583,
      "82": 8646,
      "83": 4106,
      "84": 1746,
      "85": 678,
      "86": 319,
      "87": 195,
      "88": 177,
      "89": 167,
      "90": 158,
      "91": 145,
      "92": 141,
      "93": 138,
      "94": 133,
      "95": 129,
      "96": 121,
      "97": 115,
      "98": 112,
      "99": 110,
      "100": 106,
      "101": 105,
      "102": 101,
      "103": 100,
      "104": 96,
      "105": 92,
      "106": 87,
      "107": 78,
      "108": 75,
      "109": 68,
      "110": 62,
      "111": 53,
      "112": 49,
      "113": 46,
      "114": 44,
      "115": 41,
      "116": 40,
      "117": 40,
      "118": 38,
      "119": 33,
      "120": 32,
      "121": 30,
      "122": 28,
      "123": 27,
      "124": 27,
      "125": 24,
      "126": 22,
      "127": 22,
      "128": 21,
      "129": 20,
      "130": 21,
      "131": 21,
      "132": 20,
      "133": 17,
      "134": 16,
      "135": 16,
      "136": 14,
      "137": 11,
      "138": 10,
      "139": 9,
      "140": 8,
      "141": 8,
      "142": 7,
      "143": 7,
      "144": 7,
      "145": 7,
      "146": 7,
      "147": 7,
      "148": 5,
      "149": 5,
      "150": 4,
      "151": 3,
      "152": 2,
      "153": 1
    },
    "pulls_5": {
      "1003": 9923,
      "1004": 9970,
      "1101": 10262,
      "1104": 10036,
      "1107": 10067,
      "1203": 155099,
      "1209": 10115,
      "1211": 10022
    },
    "pulls_4": {
      "1001": 7056,
      "1002": 6945,
      "1008": 6954,
      "1009": 6996,
      "1013": 7007,
      "1103": 6943,
      "1105": 6921,
      "1106": 431487,
      "1108": 6926,
      "1109": 7001,
      "1201": 430599,
      "1202": 7011,
      "1206": 7178,
      "1207": 431937,
      "21000": 26315,
      "21001": 26226,
      "21002": 26086,
      "21003": 26136,
      "21004": 26185,
      "21005": 26475,
      "21006": 26048,
      "21007": 25907,
      "21008": 26191,
      "21009": 26120,
      "21010": 26122,
      "21011": 25888,
      "21012": 26012,
      "21013": 25952,
      "21014": 26054,
      "21015": 26301,
      "21016": 26020,
      "21017": 26138,
      "21018": 26171,
      "21019": 26037,
      "21020": 26432
    },
    "by_rollnum_pulls_5": {
      "1": 1761,
      "2": 1803,
      "3": 1775,
      "4": 1737,
      "5": 1696,
      "6": 1730,
      "7": 1712,
      "8": 1705,
      "9": 1691,
      "10": 1701,
      "11": 1725,
      "12": 1642,
      "13": 1603,
      "14": 1601,
      "15": 1637,
      "16": 1652,
      "17": 1694,
      "18": 1580,
      "19": 1516,
      "20": 1527,
      "21": 1500,
      "22": 1542,
      "23": 1473,
      "24": 1493,
      "25": 1441,
      "26": 1492,
      "27": 1425,
      "28": 1403,
      "29": 1402,
      "30": 1411,
      "31": 1304,
      "32": 1404,
      "33": 1323,
      "34": 1284,
      "35": 1309,
      "36": 1245,
      "37": 1280,
      "38": 1289,
      "39": 1277,
      "40": 1229,
      "41": 1167,
      "42": 1123,
      "43": 1137,
      "44": 1168,
      "45": 1142,
      "46": 1108,
      "47": 1130,
      "48": 1193,
      "49": 1083,
      "50": 1129,
      "51": 1077,
      "52": 1076,
      "53": 1015,
      "54": 1033,
      "55": 1070,
      "56": 1054,
      "57": 985,
      "58": 1051,
      "59": 997,
      "60": 982,
      "61": 1023,
      "62": 977,
      "63": 947,
      "64": 976,
      "65": 949,
      "66": 891,
      "67": 949,
      "68": 989,
      "69": 1045,
      "70": 1034,
      "71": 996,
      "72": 951,
      "73": 985,
      "74": 8799,
      "75": 15356,
      "76": 19724,
      "77": 21278,
      "78": 19832,
      "79": 16475,
      "80": 12103,
      "81": 7926,
      "82": 4523,
      "83": 2353,
      "84": 1069,
      "85": 357,
      "86": 119,
      "87": 16,
      "88": 6,
      "89": 4,
      "90": 9,
      "91": 2,
      "92": 2,
      "93": 5,
      "94": 1,
      "95": 2,
      "96": 3,
      "97": 2,
      "98": 3,
      "99": 3,
      "100": 1,
      "101": 2,
      "102": 2,
      "103": 3,
      "104": 3,
      "105": 4,
      "106": 5,
      "107": 2,
      "108": 2,
      "109": 4,
      "110": 7,
      "111": 1,
      "112": 3,
      "113": 1,
      "114": 2,
      "115": 1,
      "117": 1,
      "118": 3,
      "119": 1,
      "120": 1,
      "121": 1,
      "122": 1,
      "124": 3,
      "125": 1,
      "127": 1,
      "128": 1,
      "132": 4,
      "133": 1,
      "135": 2,
      "136": 2,
      "137": 1,
      "138": 1,
      "139": 1,
      "141": 1,
      "147": 2,
      "149": 1,
      "150": 1,
      "151": 1,
      "153": 1
    },
    "by_rollnum_pulls_4": {
      "1": 100153,
      "2": 94292,
      "3": 90293,
      "4": 85342,
      "5": 80634,
      "6": 75908,
      "7": 72760,
      "8": 67906,
      "9": 701073,
      "10": 544427,
      "11": 6696,
      "12": 112,
      "13": 61,
      "14": 48,
      "15": 28,
      "16": 26,
      "17": 10,
      "18": 5,
      "19": 2,
      "20": 1
    },
    "by_rollnum_chance_5": {
      "1": 0.0068867346,
      "2": 0.0070536043,
      "3": 0.006959365,
      "4": 0.006828394,
      "5": 0.0066851666,
      "6": 0.0068509695,
      "7": 0.0068092416,
      "8": 0.0068130777,
      "9": 0.006793975,
      "10": 0.006872755,
      "11": 0.0070482674,
      "12": 0.0067674224,
      "13": 0.006663923,
      "14": 0.0067133233,
      "15": 0.006928602,
      "16": 0.0070598894,
      "17": 0.0073093483,
      "18": 0.0068844417,
      "19": 0.006667576,
      "20": 0.0067766975,
      "21": 0.0067436947,
      "22": 0.007005047,
      "23": 0.006761533,
      "24": 0.0069206557,
      "25": 0.006746223,
      "26": 0.0070578773,
      "27": 0.006811533,
      "28": 0.0067719873,
      "29": 0.006832492,
      "30": 0.0069446154,
      "31": 0.006500304,
      "32": 0.007067031,
      "33": 0.006730906,
      "34": 0.006597811,
      "35": 0.0067919204,
      "36": 0.006528305,
      "37": 0.0067770765,
      "38": 0.006893085,
      "39": 0.0068996446,
      "40": 0.0067098336,
      "41": 0.006445128,
      "42": 0.0062623727,
      "43": 0.006401991,
      "44": 0.0066409293,
      "45": 0.0065602777,
      "46": 0.0064305696,
      "47": 0.0066200336,
      "48": 0.007059673,
      "49": 0.006472666,
      "50": 0.0068102716,
      "51": 0.0065729246,
      "52": 0.006627534,
      "53": 0.006317847,
      "54": 0.0064884895,
      "55": 0.0067855944,
      "56": 0.0067475867,
      "57": 0.0063643646,
      "58": 0.0068565984,
      "59": 0.006564652,
      "60": 0.00652353,
      "61": 0.0068684914,
      "62": 0.006621664,
      "63": 0.006477694,
      "64": 0.006736284,
      "65": 0.006610707,
      "66": 0.0062684235,
      "67": 0.0067385733,
      "68": 0.007086304,
      "69": 0.00756063,
      "70": 0.0075601926,
      "71": 0.0073630516,
      "72": 0.0071027395,
      "73": 0.0074330647,
      "74": 0.06704409,
      "75": 0.12576164,
      "76": 0.1852819,
      "77": 0.24576399,
      "78": 0.30426043,
      "79": 0.36410448,
      "80": 0.42148703,
      "81": 0.47795936,
      "82": 0.5231321,
      "83": 0.5730638,
      "84": 0.6122566,
      "85": 0.5265487,
      "86": 0.37304077,
      "87": 0.082051285,
      "88": 0.033898305,
      "89": 0.023952097,
      "90": 0.056962024,
      "91": 0.013793103,
      "92": 0.014184397,
      "93": 0.036231883,
      "94": 0.007518797,
      "95": 0.015503876,
      "96": 0.024793388,
      "97": 0.017391304,
      "98": 0.026785715,
      "99": 0.027272727,
      "100": 0.009433962,
      "101": 0.01904762,
      "102": 0.01980198,
      "103": 0.03,
      "104": 0.03125,
      "105": 0.04347826,
      "106": 0.057471264,
      "107": 0.025641026,
      "108": 0.026666667,
      "109": 0.05882353,
      "110": 0.11290322,
      "111": 0.018867925,
      "112": 0.06122449,
      "113": 0.02173913,
      "114": 0.045454547,
      "115": 0.024390243,
      "117": 0.025,
      "118": 0.078947365,
      "119": 0.030303031,
      "120": 0.03125,
      "121": 0.033333335,
      "122": 0.035714287,
      "124": 0.11111111,
      "125": 0.041666668,
      "127": 0.045454547,
      "128": 0.04761905,
      "132": 0.2,
      "133": 0.05882353,
      "135": 0.125,
      "136": 0.14285715,
      "137": 0.09090909,
      "138": 0.1,
      "139": 0.11111111,
      "141": 0.125,
      "147": 0.2857143,
      "149": 0.2,
      "150": 0.25,
      "151": 0.33333334,
      "153": 1
    },
    "by_rollnum_chance_4": {
      "1": 0.05216908,
      "2": 0.04911612,
      "3": 0.047033068,
      "4": 0.04445412,
      "5": 0.042001754,
      "6": 0.039540008,
      "7": 0.037900236,
      "8": 0.035371818,
      "9": 0.3651846,
      "10": 0.28358868,
      "11": 0.003487905,
      "12": 5.834011e-05,
      "13": 3.1774525e-05,
      "14": 2.5002904e-05,
      "15": 1.4585027e-05,
      "16": 1.3543239e-05,
      "17": 5.2089385e-06,
      "18": 2.6044693e-06,
      "19": 1.0417876e-06,
      "20": 5.208938e-07
    },
    "by_day": {
      "1": 7402117,
      "2": 1284062,
      "3": 684106,
      "4": 1011647,
      "5": 530538,
      "6": 461259,
      "7": 352965,
      "8": 305467,
      "9": 244130,
      "10": 222543,
      "11": 353435,
      "12": 242631,
      "13": 247825,
      "14": 197908,
      "15": 178198,
      "16": 169660,
      "17": 170447,
      "18": 164294,
      "19": 173418,
      "20": 178291,
      "21": 99669
    },
    "day": 738698,
    "rateup": 1203,
    "companion_rateup": 1006,
    "companion_by_day": {
      "1": 8728522,
      "2": 1238476,
      "3": 1011218,
      "4": 877768,
      "5": 626066,
      "6": 777758,
      "7": 688303,
      "8": 411179,
      "9": 344696,
      "10": 304769,
      "11": 317183,
      "12": 283626,
      "13": 302020,
      "14": 247944,
      "15": 219884,
      "16": 210575,
      "17": 208952,
      "18": 203580,
      "19": 206500,
      "20": 205407,
      "21": 200870,
      "22": 80946
    },
    "companion_accent": "#73b0f4",
    "companion_border": "#537bbb",
    "companion_banner_id": 2005
  },
  "compat_ver": 1
}